proxy.py
proxied-1.0.1.dist-info/LICENSE
proxied-1.0.1.dist-info/WHEEL
proxied-1.0.1.dist-info/METADATA
proxied-1.0.1.dist-info/RECORD
