Metadata-Version: 2.1
Name: proxied
Version: 1.0.1
Summary: A simple to use proxy for python objects
Home-page: https://github.com/Enacero/proxied
License: MIT
Keywords: proxy,lazy
Author: Oleksii Petrenko
Author-email: oleksiiypetrenko@gmail.com
Requires-Python: >=3.6,<4.0
Classifier: License :: OSI Approved :: MIT License
Classifier: Programming Language :: Python :: 3
Classifier: Programming Language :: Python :: 3 :: Only
Classifier: Programming Language :: Python :: 3.6
Classifier: Programming Language :: Python :: 3.7
Classifier: Programming Language :: Python :: 3.8
Classifier: Programming Language :: Python :: 3.9
Classifier: Topic :: Software Development :: Libraries
Classifier: Typing :: Typed
Project-URL: Repository, https://github.com/Enacero/proxied
